ipyvue_remote_component/__init__.py
ipyvue_remote_component/force_load.py
ipyvue_remote_component/remote_component.py
ipyvue_remote_component/labextension/package.json
ipyvue_remote_component/labextension/static/261.46b417242fffc29396b0.js
ipyvue_remote_component/labextension/static/261.5336471618e57725abbf.js
ipyvue_remote_component/labextension/static/568.9d0b6b09cd73f2d88cfd.js
ipyvue_remote_component/labextension/static/568.f54744591f791ed3e979.js
ipyvue_remote_component/labextension/static/901.72d86f221dcc6e60ab1c.js
ipyvue_remote_component/labextension/static/901.72d86f221dcc6e60ab1c.js.LICENSE.txt
ipyvue_remote_component/labextension/static/901.c32f07f110af38f4b143.js
ipyvue_remote_component/labextension/static/901.c32f07f110af38f4b143.js.LICENSE.txt
ipyvue_remote_component/labextension/static/remoteEntry.507695f42026619cb03b.js
ipyvue_remote_component/labextension/static/remoteEntry.8db7edcb88e051335076.js
ipyvue_remote_component/labextension/static/style.js
ipyvue_remote_component/labextension/static/third-party-licenses.json
ipyvue_remote_component/nbextension/extension.js
ipyvue_remote_component/nbextension/index.js
ipyvue_remote_component/nbextension/index.js.LICENSE.txt
ipyvue_remote_component-1.1.1.data/data/etc/jupyter/nbconfig/notebook.d/ipyvue-remote-component.json
ipyvue_remote_component-1.1.1.data/data/share/jupyter/labextensions/ipyvue-remote-component/install.json
ipyvue_remote_component-1.1.1.data/data/share/jupyter/labextensions/ipyvue-remote-component/package.json
ipyvue_remote_component-1.1.1.data/data/share/jupyter/labextensions/ipyvue-remote-component/static/261.46b417242fffc29396b0.js
ipyvue_remote_component-1.1.1.data/data/share/jupyter/labextensions/ipyvue-remote-component/static/568.9d0b6b09cd73f2d88cfd.js
ipyvue_remote_component-1.1.1.data/data/share/jupyter/labextensions/ipyvue-remote-component/static/901.c32f07f110af38f4b143.js
ipyvue_remote_component-1.1.1.dist-info/LICENSE
ipyvue_remote_component-1.1.1.dist-info/METADATA
ipyvue_remote_component-1.1.1.dist-info/WHEEL
ipyvue_remote_component-1.1.1.dist-info/top_level.txt
ipyvue_remote_component-1.1.1.dist-info/RECORD
